yades_smtp/__init__.py
yades_smtp/controller.py
yades_smtp/main.py
yades_smtp/utils.py
yades_smtp-0.1.0.dist-info/LICENCE
yades_smtp-0.1.0.dist-info/METADATA
yades_smtp-0.1.0.dist-info/WHEEL
yades_smtp-0.1.0.dist-info/entry_points.txt
yades_smtp-0.1.0.dist-info/top_level.txt
yades_smtp-0.1.0.dist-info/RECORD
